src/__init__.py
src/main.py
src/asgard/__init__.py
src/asgard/arguments_handler.py
src/asgard/checkpoint.py
src/asgard/configuration.py
src/asgard/constants.py
src/asgard/exceptions.py
src/asgard/log_handler.py
src/asgard/scheduler.py
src/asgard/tasks.py
src/asgard/utils.py
test/__init__.py
test/context.py
test/test_args.py
test/test_asgard.py
test/test_utils.py
asgard_saga-0.9.0a0.dev0.dist-info/COPYING
asgard_saga-0.9.0a0.dev0.dist-info/METADATA
asgard_saga-0.9.0a0.dev0.dist-info/WHEEL
asgard_saga-0.9.0a0.dev0.dist-info/entry_points.txt
asgard_saga-0.9.0a0.dev0.dist-info/top_level.txt
asgard_saga-0.9.0a0.dev0.dist-info/RECORD
