Metadata-Version: 2.1
Name: asgard-saga
Version: 0.9.0a0.dev0
Summary: A tool for genomic sequential analysis automation.
Home-page: https://gitlab.com/CNCA_CeNAT/asgard
Author: Alex Sáenz Rojas
Author-email: cnca@cenat.ac.cr
License: GNU General Public License v3.0
Platform: UNKNOWN
Classifier: Intended Audience :: Science/Research
Classifier: Framework :: Sphinx
Classifier: Development Status :: 3 - Alpha
Classifier: Environment :: Console
Classifier: Programming Language :: Python :: 3.7
Classifier: Operating System :: POSIX :: Linux
Classifier: License :: OSI Approved :: GNU General Public License v3 (GPLv3)
Classifier: Topic :: Scientific/Engineering :: Bio-Informatics
Requires-Python: >=3.7
Requires-Dist: colorama (>=0.4.4)
Requires-Dist: executing (>=0.8.1)
Requires-Dist: icecream (>=2.1.1)
Requires-Dist: jsonschema (>=3.2.0)
Requires-Dist: munch (>=2.5.0)
Requires-Dist: numpy (>=1.20.2)
Requires-Dist: pydocstyle (>=5.1.1)
Requires-Dist: Pygments (>=2.10.0)
Requires-Dist: pyrsistent (>=0.17.3)
Requires-Dist: requests (>=2.24.0)
Requires-Dist: six (>=1.15.0)
Requires-Dist: snowballstemmer (>=2.1.0)
